nuvolos/__init__.py
nuvolos/sql_utils.py
nuvolos/version.py
nuvolos_odbc-0.5.1.dist-info/METADATA
nuvolos_odbc-0.5.1.dist-info/WHEEL
nuvolos_odbc-0.5.1.dist-info/top_level.txt
nuvolos_odbc-0.5.1.dist-info/RECORD
