Metadata-Version: 2.2
Name: nuvolos-odbc
Version: 0.5.1
Summary: The Nuvolos Python library for database connectivity, internal PyODBC-based version
Author-email: Alphacruncher <support@nuvolos.cloud>
License: MIT
Project-URL: Homepage, https://github.com/nuvolos-cloud/python-connector-odbc
Requires-Dist: keyring
Requires-Dist: pyodbc
Requires-Dist: pandas<3.0.0
Requires-Dist: pyarrow>10.0.0
Provides-Extra: test
Requires-Dist: pytest; extra == "test"
Requires-Dist: pytest-runner; extra == "test"
